pruna_pro/__init__.py
pruna_pro/py.typed
pruna_pro/smash.cp312-win32.pyd
pruna_pro/smash.py
pruna_pro/algorithms/__init__.py
pruna_pro/algorithms/adaptive_caching.cp312-win32.pyd
pruna_pro/algorithms/adaptive_caching.py
pruna_pro/algorithms/auto_caching.cp312-win32.pyd
pruna_pro/algorithms/auto_caching.py
pruna_pro/algorithms/bottleneck.cp312-win32.pyd
pruna_pro/algorithms/bottleneck.py
pruna_pro/algorithms/denoise.cp312-win32.pyd
pruna_pro/algorithms/denoise.py
pruna_pro/algorithms/diffusers_higgs.cp312-win32.pyd
pruna_pro/algorithms/diffusers_higgs.py
pruna_pro/algorithms/distillation_perp.cp312-win32.pyd
pruna_pro/algorithms/distillation_perp.py
pruna_pro/algorithms/flux_caching.cp312-win32.pyd
pruna_pro/algorithms/flux_caching.py
pruna_pro/algorithms/fp4.cp312-win32.pyd
pruna_pro/algorithms/fp4.py
pruna_pro/algorithms/huggingface_higgs.cp312-win32.pyd
pruna_pro/algorithms/huggingface_higgs.py
pruna_pro/algorithms/hyper.cp312-win32.pyd
pruna_pro/algorithms/hyper.py
pruna_pro/algorithms/ipex_llm.cp312-win32.pyd
pruna_pro/algorithms/ipex_llm.py
pruna_pro/algorithms/padding_pruning.cp312-win32.pyd
pruna_pro/algorithms/padding_pruning.py
pruna_pro/algorithms/periodic_caching.cp312-win32.pyd
pruna_pro/algorithms/periodic_caching.py
pruna_pro/algorithms/perp.cp312-win32.pyd
pruna_pro/algorithms/perp.py
pruna_pro/algorithms/prores.cp312-win32.pyd
pruna_pro/algorithms/prores.py
pruna_pro/algorithms/stable_fast.cp312-win32.pyd
pruna_pro/algorithms/stable_fast.py
pruna_pro/algorithms/taylor_auto_caching.cp312-win32.pyd
pruna_pro/algorithms/taylor_auto_caching.py
pruna_pro/algorithms/taylor_caching.cp312-win32.pyd
pruna_pro/algorithms/taylor_caching.py
pruna_pro/algorithms/torch_compile.cp312-win32.pyd
pruna_pro/algorithms/torch_compile.py
pruna_pro/algorithms/torchao_autoquant.cp312-win32.pyd
pruna_pro/algorithms/torchao_autoquant.py
pruna_pro/algorithms/upscale.cp312-win32.pyd
pruna_pro/algorithms/upscale.py
pruna_pro/algorithms/x_fast.cp312-win32.pyd
pruna_pro-0.3.0.dist-info/METADATA
pruna_pro-0.3.0.dist-info/WHEEL
pruna_pro-0.3.0.dist-info/entry_points.txt
pruna_pro-0.3.0.dist-info/top_level.txt
pruna_pro-0.3.0.dist-info/RECORD
