Metadata-Version: 2.4
Name: pruna_pro
Version: 0.3.0
Summary: Smash your AI models - Pro Version
Author-email: Pruna AI <hello@pruna.ai>
License: All Rights Reserved
Requires-Python: >=3.9
Requires-Dist: pruna==0.3.0
Requires-Dist: torch==2.7.0
Requires-Dist: torchvision==0.22.0
Requires-Dist: diffusers>=0.33.0
Requires-Dist: cython
Requires-Dist: lago-python-client
Requires-Dist: peft
Requires-Dist: optuna
Requires-Dist: torchao
Requires-Dist: aenum
Requires-Dist: realesrgan
Requires-Dist: keyring
Requires-Dist: keyrings-alt
Requires-Dist: trl<=0.21.0
Requires-Dist: urllib3>=2.0.0
Requires-Dist: requests>=2.30.0
Requires-Dist: cryptography>=41.0
Provides-Extra: fp-quant-with-blackwell
Requires-Dist: qutlass; extra == "fp-quant-with-blackwell"
Requires-Dist: fp_quant; python_version >= "3.11" and extra == "fp-quant-with-blackwell"
Provides-Extra: fp-quant-without-blackwell
Requires-Dist: fp_quant; python_version >= "3.11" and extra == "fp-quant-without-blackwell"
Provides-Extra: vllm
Requires-Dist: vllm>=0.9.1; extra != "intel" and extra == "vllm"
Provides-Extra: higgs
Requires-Dist: fast_hadamard_transform==1.0.4.post1+cu126torch2.7cxx11abifalse; extra == "higgs"
Requires-Dist: flute-kernel==0.4.1+cu126torch2.7; extra == "higgs"
Provides-Extra: intel
Requires-Dist: intel-extension-for-pytorch==2.7.0; extra != "vllm" and extra == "intel"
Requires-Dist: oneccl_bind_pt==2.7.0; extra != "vllm" and extra == "intel"
Requires-Dist: transformers<=4.48.0; extra != "vllm" and extra == "intel"
Provides-Extra: tests
Requires-Dist: pytest; extra == "tests"
Requires-Dist: pytest-cov; extra == "tests"
Requires-Dist: coverage; extra == "tests"
Requires-Dist: ruff; extra == "tests"
Requires-Dist: docutils; extra == "tests"
Requires-Dist: numpydoc-validation; extra == "tests"
Requires-Dist: mypy; extra == "tests"
Requires-Dist: pyarrow<20.0.0; extra == "tests"
Provides-Extra: cpu
Provides-Extra: docs
Requires-Dist: sphinx>=7.0.0; extra == "docs"
Requires-Dist: nbsphinx; extra == "docs"
Requires-Dist: sphinxawesome_theme; extra == "docs"
Requires-Dist: sphinx-autobuild; extra == "docs"
Requires-Dist: sphinx-design; extra == "docs"
Requires-Dist: sphinx-tabs; extra == "docs"
Requires-Dist: sphinx_togglebutton; extra == "docs"
Requires-Dist: sphinxext-opengraph[social-cards]; extra == "docs"
Requires-Dist: sphinxcontrib-googleanalytics; extra == "docs"
Requires-Dist: pandoc; extra == "docs"
Requires-Dist: nbstripout; extra == "docs"
Requires-Dist: sphinxcontrib-mermaid; extra == "docs"
Requires-Dist: nbformat; extra == "docs"
Requires-Dist: pyarrow<20.0.0; extra == "docs"
Requires-Dist: ipython; extra == "docs"
Provides-Extra: dev
Requires-Dist: pruna_pro[docs]; extra == "dev"
Requires-Dist: pruna_pro[tests]; extra == "dev"
Requires-Dist: ruff; extra == "dev"
Requires-Dist: numpydoc-validation; extra == "dev"
Requires-Dist: pre-commit; extra == "dev"
Provides-Extra: full
Requires-Dist: pruna_pro[higgs]; extra == "full"
